thriftpy2/__init__.py
thriftpy2/_compat.py
thriftpy2/hook.py
thriftpy2/http.py
thriftpy2/rpc.py
thriftpy2/server.py
thriftpy2/thrift.py
thriftpy2/tornado.py
thriftpy2/utils.py
thriftpy2/contrib/__init__.py
thriftpy2/contrib/aio/__init__.py
thriftpy2/contrib/aio/client.py
thriftpy2/contrib/aio/processor.py
thriftpy2/contrib/aio/rpc.py
thriftpy2/contrib/aio/server.py
thriftpy2/contrib/aio/socket.py
thriftpy2/contrib/aio/protocol/__init__.py
thriftpy2/contrib/aio/protocol/base.py
thriftpy2/contrib/aio/protocol/binary.py
thriftpy2/contrib/aio/protocol/compact.py
thriftpy2/contrib/aio/transport/__init__.py
thriftpy2/contrib/aio/transport/base.py
thriftpy2/contrib/aio/transport/buffered.py
thriftpy2/contrib/aio/transport/framed.py
thriftpy2/contrib/tracking/__init__.py
thriftpy2/contrib/tracking/tracker.py
thriftpy2/contrib/tracking/tracking.thrift
thriftpy2/parser/__init__.py
thriftpy2/parser/exc.py
thriftpy2/parser/lexer.py
thriftpy2/parser/parser.py
thriftpy2/protocol/__init__.py
thriftpy2/protocol/apache_json.py
thriftpy2/protocol/base.py
thriftpy2/protocol/binary.py
thriftpy2/protocol/compact.py
thriftpy2/protocol/exc.py
thriftpy2/protocol/json.py
thriftpy2/protocol/multiplex.py
thriftpy2/protocol/cybin/__init__.py
thriftpy2/protocol/cybin/cybin.c
thriftpy2/protocol/cybin/cybin.cp310-win_amd64.pyd
thriftpy2/protocol/cybin/cybin.pyx
thriftpy2/protocol/cybin/endian_port.h
thriftpy2/transport/__init__.py
thriftpy2/transport/_ssl.py
thriftpy2/transport/base.py
thriftpy2/transport/cybase.c
thriftpy2/transport/cybase.cp310-win_amd64.pyd
thriftpy2/transport/cybase.pxd
thriftpy2/transport/cybase.pyx
thriftpy2/transport/socket.py
thriftpy2/transport/sslsocket.py
thriftpy2/transport/buffered/__init__.py
thriftpy2/transport/buffered/cybuffered.c
thriftpy2/transport/buffered/cybuffered.cp310-win_amd64.pyd
thriftpy2/transport/buffered/cybuffered.pyx
thriftpy2/transport/framed/__init__.py
thriftpy2/transport/framed/cyframed.c
thriftpy2-0.5.3.dist-info/licenses/LICENSE
thriftpy2-0.5.3.dist-info/METADATA
thriftpy2-0.5.3.dist-info/WHEEL
thriftpy2-0.5.3.dist-info/top_level.txt
thriftpy2-0.5.3.dist-info/RECORD
