Metadata-Version: 2.4
Name: thriftpy2
Version: 0.5.3
Summary: Pure python implementation of Apache Thrift.
Author-email: ThriftPy Organization <gotzehsing@gmail.com>
License: The MIT License (MIT)
Project-URL: Homepage, https://thriftpy2.readthedocs.io/
Project-URL: Source, https://github.com/Thriftpy/thriftpy2
Keywords: thrift python thriftpy thriftpy2
Classifier: Development Status :: 4 - Beta
Classifier: Intended Audience :: Developers
Classifier: License :: OSI Approved :: MIT License
Classifier: Programming Language :: Python :: 3
Classifier: Programming Language :: Python :: 3.10
Classifier: Programming Language :: Python :: 3.11
Classifier: Programming Language :: Python :: 3.12
Classifier: Programming Language :: Python :: 3.7
Classifier: Programming Language :: Python :: 3.8
Classifier: Programming Language :: Python :: 3.9
Classifier: Programming Language :: Python :: Implementation :: CPython
Classifier: Programming Language :: Python :: Implementation :: PyPy
Classifier: Topic :: Software Development
Requires-Python: >=3.7
License-File: LICENSE
Requires-Dist: ply<4.0,>=3.4
Requires-Dist: six~=1.15
Provides-Extra: dev
Requires-Dist: flake8>=4.0; extra == "dev"
Requires-Dist: sphinx-rtd-theme>=0.1.9; extra == "dev"
Requires-Dist: sphinx>=1.3; extra == "dev"
Requires-Dist: pytest-reraise; extra == "dev"
Requires-Dist: pytest<8.2.0,>=6.1.1; extra == "dev"
Requires-Dist: tornado<7.0,>=4.0; python_version >= "3.12" and extra == "dev"
Requires-Dist: tornado<6.0,>=4.0; python_version < "3.12" and extra == "dev"
Provides-Extra: tornado
Requires-Dist: tornado<7.0,>=4.0; python_version >= "3.12" and extra == "tornado"
Requires-Dist: tornado<6.0,>=4.0; python_version < "3.12" and extra == "tornado"
Dynamic: license-file
